refspy/__init__.py
refspy/book.py
refspy/config.py
refspy/format.py
refspy/formatter.py
refspy/index.py
refspy/indexers.py
refspy/init.py
refspy/language.py
refspy/library.py
refspy/manager.py
refspy/matcher.py
refspy/navigator.py
refspy/number.py
refspy/py.typed
refspy/range.py
refspy/reference.py
refspy/utils.py
refspy/verse.py
refspy/languages/__init__.py
refspy/languages/english.py
refspy/libraries/__init__.py
refspy/libraries/en_US.py
refspy-0.10.4.dist-info/METADATA
refspy-0.10.4.dist-info/WHEEL
refspy-0.10.4.dist-info/top_level.txt
refspy-0.10.4.dist-info/RECORD
