Metadata-Version: 2.4
Name: refspy
Version: 0.10.4
Summary: A Python package for working with biblical references in human text.
Author-email: Nigel Chapman <nigel@chapman.id.au>
Project-URL: Homepage, https://github.com/eukras/refspy
Project-URL: Issues, https://github.com/eukras/refspy/issues
Classifier: Development Status :: 4 - Beta
Classifier: Intended Audience :: Developers
Classifier: Operating System :: OS Independent
Classifier: Programming Language :: Python :: 3
Classifier: Topic :: Religion
Classifier: Topic :: Text Processing :: Indexing
Requires-Python: >=3.11
Requires-Dist: pydantic>=2.7.1
